pymldd/__init__.py
pymldd/main.py
pymldd-0.0.2.dist-info/METADATA
pymldd-0.0.2.dist-info/WHEEL
pymldd-0.0.2.dist-info/entry_points.txt
pymldd-0.0.2.dist-info/top_level.txt
pymldd-0.0.2.dist-info/RECORD
