Metadata-Version: 2.1
Name: pymldd
Version: 0.0.2
Summary: A Python library for solving combinatorial optimization using Multivalued  Decision Diagrams and Machine Learning
Home-page: https://github.com/AIM-BENMHAMED/pymldd
Author: Abdelouahed Ben Mhamed
Author-email: a.benmhamed@intelligentica.net
Classifier: Programming Language :: Python :: 3
Classifier: License :: OSI Approved :: MIT License
Classifier: Operating System :: OS Independent
Requires-Python: >=3.6
